LICENSE
MANIFEST.in
README.md
setup.py
bin/openQCD-input-file-editor
docs/parms.pdf
examples/48x24v1.in
examples/48x24v2.in
examples/48x24v3.in
examples/64x32v1.in
examples/64x32v2.in
examples/INDEX
examples/README.md
openQCD_input_file_editor.egg-info/PKG-INFO
openQCD_input_file_editor.egg-info/SOURCES.txt
openQCD_input_file_editor.egg-info/dependency_links.txt
openQCD_input_file_editor.egg-info/not-zip-safe
openQCD_input_file_editor.egg-info/top_level.txt
openqcd_input_file_editor/__init__.py
openqcd_input_file_editor/consistency.py
openqcd_input_file_editor/gui.py
openqcd_input_file_editor/main.py
openqcd_input_file_editor/utils.py