Metadata-Version: 1.0
Name: openQCD-input-file-editor
Version: 0.1
Summary: An input file editor with a graphical user interface for the openQCD lattice QCD simulation program
Home-page: http://lkeegan.github.io/openQCD-input-file-editor/
Author: Liam Keegan
Author-email: liam.r.g.keegan@gmail.com
License: MIT
Platform: UNKNOWN
